Metadata-Version: 1.0
Name: kewodict
Version: 0.1.1
Summary: kewodict
Home-page: UNKNOWN
Author: melon
Author-email: melonchild@outlook.com
License: UNKNOWN
Platform: UNKNOWN
